setup.py
datamash/__init__.py
datamash/client.py
datamash/repository.py
datamash/resource.py
datamash.egg-info/PKG-INFO
datamash.egg-info/SOURCES.txt
datamash.egg-info/dependency_links.txt
datamash.egg-info/requires.txt
datamash.egg-info/top_level.txt