Metadata-Version: 1.0
Name: datamash
Version: 0.1.0
Summary: A client for the DatamashIO API
Home-page: https://github.com/datamash
Author: DatamashIO Ltd
Author-email: dev@datamash.io
License: UNKNOWN
Platform: UNKNOWN
